{
    "PL": "ILLUMINA",
    "base input url": "/scratch/lg1883/split_seq/raw",
    "base output url": "/scratch/lg1883/split_seq/full_run_999",
    "cellular": [
        {
            "algorithm": "pamld",
            "codec": {
                "A1": {
                    "barcode": [
                        "AACGTGAT"
                    ],
                    "concentration": 0.003620189913598
                },
                "A10": {
                    "barcode": [
                        "ACAAGCTA"
                    ],
                    "concentration": 0.008332333405513
                },
                "A11": {
                    "barcode": [
                        "CTGTAGCC"
                    ],
                    "concentration": 0.00293277259984
                },
                "A12": {
                    "barcode": [
                        "AGTACAAG"
                    ],
                    "concentration": 0.0100385211679
                },
                "A2": {
                    "barcode": [
                        "AAACATCG"
                    ],
                    "concentration": 0.001510102882454
                },
                "A3": {
                    "barcode": [
                        "ATGCCTAA"
                    ],
                    "concentration": 0.001369068717245
                },
                "A4": {
                    "barcode": [
                        "AGTGGTCA"
                    ],
                    "concentration": 0.005219455734203
                },
                "A5": {
                    "barcode": [
                        "ACCACTGT"
                    ],
                    "concentration": 0.015097179393025
                },
                "A6": {
                    "barcode": [
                        "ACATTGGC"
                    ],
                    "concentration": 0.006032613822596
                },
                "A7": {
                    "barcode": [
                        "CAGATCTG"
                    ],
                    "concentration": 0.010516674378251
                },
                "A8": {
                    "barcode": [
                        "CATCAAGT"
                    ],
                    "concentration": 0.012255722337835
                },
                "A9": {
                    "barcode": [
                        "CGCTGATC"
                    ],
                    "concentration": 0.005530573269697
                },
                "B1": {
                    "barcode": [
                        "AACAACCA"
                    ],
                    "concentration": 0.00209528786145
                },
                "B10": {
                    "barcode": [
                        "ACGTATCA"
                    ],
                    "concentration": 0.013567197848496
                },
                "B11": {
                    "barcode": [
                        "ACTATGCA"
                    ],
                    "concentration": 0.009905427484834
                },
                "B12": {
                    "barcode": [
                        "AGAGTCAA"
                    ],
                    "concentration": 0.007909313280031
                },
                "B2": {
                    "barcode": [
                        "AACCGAGA"
                    ],
                    "concentration": 0.001659978110078
                },
                "B3": {
                    "barcode": [
                        "AACGCTTA"
                    ],
                    "concentration": 0.004003798669547
                },
                "B4": {
                    "barcode": [
                        "AAGACGGA"
                    ],
                    "concentration": 0.007622489446475
                },
                "B5": {
                    "barcode": [
                        "AAGGTACA"
                    ],
                    "concentration": 0.007132612218575
                },
                "B6": {
                    "barcode": [
                        "ACACAGAA"
                    ],
                    "concentration": 0.009459662216172
                },
                "B7": {
                    "barcode": [
                        "ACAGCAGA"
                    ],
                    "concentration": 0.008592996480471
                },
                "B8": {
                    "barcode": [
                        "ACCTCCAA"
                    ],
                    "concentration": 0.008852890767394
                },
                "B9": {
                    "barcode": [
                        "ACGCTCGA"
                    ],
                    "concentration": 0.008090785695936
                },
                "C1": {
                    "barcode": [
                        "AGATCGCA"
                    ],
                    "concentration": 0.007505068056658
                },
                "C10": {
                    "barcode": [
                        "CAGCGTTA"
                    ],
                    "concentration": 0.007441181770864
                },
                "C11": {
                    "barcode": [
                        "CATACCAA"
                    ],
                    "concentration": 0.006389463263548
                },
                "C12": {
                    "barcode": [
                        "CCAGTTCA"
                    ],
                    "concentration": 0.013584923904069
                },
                "C2": {
                    "barcode": [
                        "AGCAGGAA"
                    ],
                    "concentration": 0.005991895513402
                },
                "C3": {
                    "barcode": [
                        "AGTCACTA"
                    ],
                    "concentration": 0.008016927131046
                },
                "C4": {
                    "barcode": [
                        "ATCCTGTA"
                    ],
                    "concentration": 0.014763475963301
                },
                "C5": {
                    "barcode": [
                        "ATTGAGGA"
                    ],
                    "concentration": 0.016339085077768
                },
                "C6": {
                    "barcode": [
                        "CAACCACA"
                    ],
                    "concentration": 0.009924141982168
                },
                "C7": {
                    "barcode": [
                        "GACTAGTA"
                    ],
                    "concentration": 0.007826410473032
                },
                "C8": {
                    "barcode": [
                        "CAATGGAA"
                    ],
                    "concentration": 0.004951362872011
                },
                "C9": {
                    "barcode": [
                        "CACTTCGA"
                    ],
                    "concentration": 0.013535024069188
                },
                "D1": {
                    "barcode": [
                        "CCGAAGTA"
                    ],
                    "concentration": 0.005907180563175
                },
                "D10": {
                    "barcode": [
                        "GAATCTGA"
                    ],
                    "concentration": 0.007341986148844
                },
                "D11": {
                    "barcode": [
                        "CAAGACTA"
                    ],
                    "concentration": 0.004869421050056
                },
                "D12": {
                    "barcode": [
                        "GAGCTGAA"
                    ],
                    "concentration": 0.005004738727083
                },
                "D2": {
                    "barcode": [
                        "CCGTGAGA"
                    ],
                    "concentration": 0.006296203783435
                },
                "D3": {
                    "barcode": [
                        "CCTCCTGA"
                    ],
                    "concentration": 0.004819383931597
                },
                "D4": {
                    "barcode": [
                        "CGAACTTA"
                    ],
                    "concentration": 0.011094270321062
                },
                "D5": {
                    "barcode": [
                        "CGACTGGA"
                    ],
                    "concentration": 0.004979769589942
                },
                "D6": {
                    "barcode": [
                        "CGCATACA"
                    ],
                    "concentration": 0.008667107647145
                },
                "D7": {
                    "barcode": [
                        "CTCAATGA"
                    ],
                    "concentration": 0.010550468103777
                },
                "D8": {
                    "barcode": [
                        "CTGAGCCA"
                    ],
                    "concentration": 0.004823941746382
                },
                "D9": {
                    "barcode": [
                        "CTGGCATA"
                    ],
                    "concentration": 0.00549889371127
                },
                "E1": {
                    "barcode": [
                        "GATAGACA"
                    ],
                    "concentration": 0.001878753219759
                },
                "E10": {
                    "barcode": [
                        "GTCTGTCA"
                    ],
                    "concentration": 0.005654221842606
                },
                "E11": {
                    "barcode": [
                        "GTGTTCTA"
                    ],
                    "concentration": 0.005844546303611
                },
                "E12": {
                    "barcode": [
                        "TAGGATGA"
                    ],
                    "concentration": 0.002777477416563
                },
                "E2": {
                    "barcode": [
                        "GCCACATA"
                    ],
                    "concentration": 0.000474100599132
                },
                "E3": {
                    "barcode": [
                        "GCGAGTAA"
                    ],
                    "concentration": 0.001126241524722
                },
                "E4": {
                    "barcode": [
                        "GCTAACGA"
                    ],
                    "concentration": 0.003418783922188
                },
                "E5": {
                    "barcode": [
                        "GCTCGGTA"
                    ],
                    "concentration": 0.002469111043969
                },
                "E6": {
                    "barcode": [
                        "GGAGAACA"
                    ],
                    "concentration": 0.006567360815085
                },
                "E7": {
                    "barcode": [
                        "GGTGCGAA"
                    ],
                    "concentration": 0.001883755833337
                },
                "E8": {
                    "barcode": [
                        "GTACGCAA"
                    ],
                    "concentration": 0.004168352257316
                },
                "E9": {
                    "barcode": [
                        "GTCGTAGA"
                    ],
                    "concentration": 0.005052623239042
                },
                "F1": {
                    "barcode": [
                        "TATCAGCA"
                    ],
                    "concentration": 0.00180119348961
                },
                "F10": {
                    "barcode": [
                        "AAGAGATC"
                    ],
                    "concentration": 0.004466938547823
                },
                "F11": {
                    "barcode": [
                        "AAGGACAC"
                    ],
                    "concentration": 0.00408670696789
                },
                "F12": {
                    "barcode": [
                        "AATCCGTC"
                    ],
                    "concentration": 0.007148740293302
                },
                "F2": {
                    "barcode": [
                        "TCCGTCTA"
                    ],
                    "concentration": 0.000647929065421
                },
                "F3": {
                    "barcode": [
                        "TCTTCACA"
                    ],
                    "concentration": 0.002148916318306
                },
                "F4": {
                    "barcode": [
                        "TGAAGAGA"
                    ],
                    "concentration": 0.006942079086532
                },
                "F5": {
                    "barcode": [
                        "TGGAACAA"
                    ],
                    "concentration": 0.004006017172165
                },
                "F6": {
                    "barcode": [
                        "TGGCTTCA"
                    ],
                    "concentration": 0.006444189989027
                },
                "F7": {
                    "barcode": [
                        "TGGTGGTA"
                    ],
                    "concentration": 0.011750474840557
                },
                "F8": {
                    "barcode": [
                        "TTCACGCA"
                    ],
                    "concentration": 0.00507850393914
                },
                "F9": {
                    "barcode": [
                        "AACTCACC"
                    ],
                    "concentration": 0.006366070141881
                },
                "G1": {
                    "barcode": [
                        "AATGTTGC"
                    ],
                    "concentration": 0.005148441685046
                },
                "G10": {
                    "barcode": [
                        "ATTGGCTC"
                    ],
                    "concentration": 0.004735701353875
                },
                "G11": {
                    "barcode": [
                        "CAAGGAGC"
                    ],
                    "concentration": 0.005560083747595
                },
                "G12": {
                    "barcode": [
                        "CACCTTAC"
                    ],
                    "concentration": 0.006144895315258
                },
                "G2": {
                    "barcode": [
                        "ACACGACC"
                    ],
                    "concentration": 0.006581715185987
                },
                "G3": {
                    "barcode": [
                        "ACAGATTC"
                    ],
                    "concentration": 0.003730521979455
                },
                "G4": {
                    "barcode": [
                        "AGATGTAC"
                    ],
                    "concentration": 0.007211132933769
                },
                "G5": {
                    "barcode": [
                        "AGCACCTC"
                    ],
                    "concentration": 0.009887778308064
                },
                "G6": {
                    "barcode": [
                        "AGCCATGC"
                    ],
                    "concentration": 0.005894314346258
                },
                "G7": {
                    "barcode": [
                        "AGGCTAAC"
                    ],
                    "concentration": 0.005369891078824
                },
                "G8": {
                    "barcode": [
                        "ATAGCGAC"
                    ],
                    "concentration": 0.003967478926188
                },
                "G9": {
                    "barcode": [
                        "ATCATTCC"
                    ],
                    "concentration": 0.009048514374504
                },
                "H1": {
                    "barcode": [
                        "CCATCCTC"
                    ],
                    "concentration": 0.008096979930969
                },
                "H10": {
                    "barcode": [
                        "GAGTTAGC"
                    ],
                    "concentration": 0.004255104495838
                },
                "H11": {
                    "barcode": [
                        "GATGAATC"
                    ],
                    "concentration": 0.002313557767564
                },
                "H12": {
                    "barcode": [
                        "GCCAAGAC"
                    ],
                    "concentration": 0.002019979581978
                },
                "H2": {
                    "barcode": [
                        "CCGACAAC"
                    ],
                    "concentration": 0.002069626815076
                },
                "H3": {
                    "barcode": [
                        "CCTAATCC"
                    ],
                    "concentration": 0.003590673944358
                },
                "H4": {
                    "barcode": [
                        "CCTCTATC"
                    ],
                    "concentration": 0.005287570354195
                },
                "H5": {
                    "barcode": [
                        "CGACACAC"
                    ],
                    "concentration": 0.005439427956683
                },
                "H6": {
                    "barcode": [
                        "CGGATTGC"
                    ],
                    "concentration": 0.003565007406641
                },
                "H7": {
                    "barcode": [
                        "CTAAGGTC"
                    ],
                    "concentration": 0.005172307062222
                },
                "H8": {
                    "barcode": [
                        "GAACAGGC"
                    ],
                    "concentration": 0.009379807104601
                },
                "H9": {
                    "barcode": [
                        "GACAGTGC"
                    ],
                    "concentration": 0.008570026192223
                }
            },
            "comment": "BC1: First round cellular barcode",
            "confidence threshold": 0.999,
            "noise": 0.39728640118135,
            "transform": {
                "token": [
                    "1:86:94"
                ]
            }
        },
        {
            "algorithm": "pamld",
            "codec": {
                "A1": {
                    "barcode": [
                        "AACGTGAT"
                    ],
                    "concentration": 0.00593008804323
                },
                "A10": {
                    "barcode": [
                        "ACAAGCTA"
                    ],
                    "concentration": 0.008099036764494
                },
                "A11": {
                    "barcode": [
                        "CTGTAGCC"
                    ],
                    "concentration": 0.007289636895434
                },
                "A12": {
                    "barcode": [
                        "AGTACAAG"
                    ],
                    "concentration": 0.005462126259825
                },
                "A2": {
                    "barcode": [
                        "AAACATCG"
                    ],
                    "concentration": 0.004590626339103
                },
                "A3": {
                    "barcode": [
                        "ATGCCTAA"
                    ],
                    "concentration": 0.005659182992123
                },
                "A4": {
                    "barcode": [
                        "AGTGGTCA"
                    ],
                    "concentration": 0.008608338260574
                },
                "A5": {
                    "barcode": [
                        "ACCACTGT"
                    ],
                    "concentration": 0.007441524689352
                },
                "A6": {
                    "barcode": [
                        "ACATTGGC"
                    ],
                    "concentration": 0.009416160112235
                },
                "A7": {
                    "barcode": [
                        "CAGATCTG"
                    ],
                    "concentration": 0.008547584590729
                },
                "A8": {
                    "barcode": [
                        "CATCAAGT"
                    ],
                    "concentration": 0.003862747717487
                },
                "A9": {
                    "barcode": [
                        "CGCTGATC"
                    ],
                    "concentration": 0.000848843065411
                },
                "B1": {
                    "barcode": [
                        "AACAACCA"
                    ],
                    "concentration": 0.008203475457276
                },
                "B10": {
                    "barcode": [
                        "ACGTATCA"
                    ],
                    "concentration": 0.010229657035642
                },
                "B11": {
                    "barcode": [
                        "ACTATGCA"
                    ],
                    "concentration": 0.008077928972135
                },
                "B12": {
                    "barcode": [
                        "AGAGTCAA"
                    ],
                    "concentration": 0.009248434235437
                },
                "B2": {
                    "barcode": [
                        "AACCGAGA"
                    ],
                    "concentration": 0.008195845960312
                },
                "B3": {
                    "barcode": [
                        "AACGCTTA"
                    ],
                    "concentration": 0.010970659260669
                },
                "B4": {
                    "barcode": [
                        "AAGACGGA"
                    ],
                    "concentration": 0.007534128251644
                },
                "B5": {
                    "barcode": [
                        "AAGGTACA"
                    ],
                    "concentration": 0.00876255688753
                },
                "B6": {
                    "barcode": [
                        "ACACAGAA"
                    ],
                    "concentration": 0.01450436863472
                },
                "B7": {
                    "barcode": [
                        "ACAGCAGA"
                    ],
                    "concentration": 0.010319198665092
                },
                "B8": {
                    "barcode": [
                        "ACCTCCAA"
                    ],
                    "concentration": 0.01082634305482
                },
                "B9": {
                    "barcode": [
                        "ACGCTCGA"
                    ],
                    "concentration": 0.011632579650471
                },
                "C1": {
                    "barcode": [
                        "AGATCGCA"
                    ],
                    "concentration": 0.004934540030035
                },
                "C10": {
                    "barcode": [
                        "CAGCGTTA"
                    ],
                    "concentration": 0.008825511095398
                },
                "C11": {
                    "barcode": [
                        "CATACCAA"
                    ],
                    "concentration": 0.009877708485479
                },
                "C12": {
                    "barcode": [
                        "CCAGTTCA"
                    ],
                    "concentration": 0.009372402703179
                },
                "C2": {
                    "barcode": [
                        "AGCAGGAA"
                    ],
                    "concentration": 0.005914829049302
                },
                "C3": {
                    "barcode": [
                        "AGTCACTA"
                    ],
                    "concentration": 0.009413496303049
                },
                "C4": {
                    "barcode": [
                        "ATCCTGTA"
                    ],
                    "concentration": 0.008365685511791
                },
                "C5": {
                    "barcode": [
                        "ATTGAGGA"
                    ],
                    "concentration": 0.008760906484012
                },
                "C6": {
                    "barcode": [
                        "CAACCACA"
                    ],
                    "concentration": 0.007337701278583
                },
                "C7": {
                    "barcode": [
                        "GACTAGTA"
                    ],
                    "concentration": 0.007892099326925
                },
                "C8": {
                    "barcode": [
                        "CAATGGAA"
                    ],
                    "concentration": 0.007714782289332
                },
                "C9": {
                    "barcode": [
                        "CACTTCGA"
                    ],
                    "concentration": 0.010234716825374
                },
                "D1": {
                    "barcode": [
                        "CCGAAGTA"
                    ],
                    "concentration": 0.008184474100986
                },
                "D10": {
                    "barcode": [
                        "GAATCTGA"
                    ],
                    "concentration": 0.009660890342639
                },
                "D11": {
                    "barcode": [
                        "CAAGACTA"
                    ],
                    "concentration": 0.007198944326688
                },
                "D12": {
                    "barcode": [
                        "GAGCTGAA"
                    ],
                    "concentration": 0.012293139181231
                },
                "D2": {
                    "barcode": [
                        "CCGTGAGA"
                    ],
                    "concentration": 0.007705741263044
                },
                "D3": {
                    "barcode": [
                        "CCTCCTGA"
                    ],
                    "concentration": 0.008975726769962
                },
                "D4": {
                    "barcode": [
                        "CGAACTTA"
                    ],
                    "concentration": 0.012039773286807
                },
                "D5": {
                    "barcode": [
                        "CGACTGGA"
                    ],
                    "concentration": 0.010142048115574
                },
                "D6": {
                    "barcode": [
                        "CGCATACA"
                    ],
                    "concentration": 0.015812009400846
                },
                "D7": {
                    "barcode": [
                        "CTCAATGA"
                    ],
                    "concentration": 0.007483472445428
                },
                "D8": {
                    "barcode": [
                        "CTGAGCCA"
                    ],
                    "concentration": 0.00822430094377
                },
                "D9": {
                    "barcode": [
                        "CTGGCATA"
                    ],
                    "concentration": 0.007039398081359
                },
                "E1": {
                    "barcode": [
                        "GATAGACA"
                    ],
                    "concentration": 0.007178741360819
                },
                "E10": {
                    "barcode": [
                        "GTCTGTCA"
                    ],
                    "concentration": 0.008682215533829
                },
                "E11": {
                    "barcode": [
                        "GTGTTCTA"
                    ],
                    "concentration": 0.007927807399526
                },
                "E12": {
                    "barcode": [
                        "TAGGATGA"
                    ],
                    "concentration": 0.006368885459209
                },
                "E2": {
                    "barcode": [
                        "GCCACATA"
                    ],
                    "concentration": 0.008355363251193
                },
                "E3": {
                    "barcode": [
                        "GCGAGTAA"
                    ],
                    "concentration": 0.006898636033963
                },
                "E4": {
                    "barcode": [
                        "GCTAACGA"
                    ],
                    "concentration": 0.008147274874329
                },
                "E5": {
                    "barcode": [
                        "GCTCGGTA"
                    ],
                    "concentration": 0.004312185892988
                },
                "E6": {
                    "barcode": [
                        "GGAGAACA"
                    ],
                    "concentration": 0.008732437023331
                },
                "E7": {
                    "barcode": [
                        "GGTGCGAA"
                    ],
                    "concentration": 0.003714508183977
                },
                "E8": {
                    "barcode": [
                        "GTACGCAA"
                    ],
                    "concentration": 0.007411795710196
                },
                "E9": {
                    "barcode": [
                        "GTCGTAGA"
                    ],
                    "concentration": 0.006920612459752
                },
                "F1": {
                    "barcode": [
                        "TATCAGCA"
                    ],
                    "concentration": 0.00734643828317
                },
                "F10": {
                    "barcode": [
                        "AAGAGATC"
                    ],
                    "concentration": 0.005386309038575
                },
                "F11": {
                    "barcode": [
                        "AAGGACAC"
                    ],
                    "concentration": 0.00743695712523
                },
                "F12": {
                    "barcode": [
                        "AATCCGTC"
                    ],
                    "concentration": 0.009252654346186
                },
                "F2": {
                    "barcode": [
                        "TCCGTCTA"
                    ],
                    "concentration": 0.008636554369838
                },
                "F3": {
                    "barcode": [
                        "TCTTCACA"
                    ],
                    "concentration": 0.006456878025708
                },
                "F4": {
                    "barcode": [
                        "TGAAGAGA"
                    ],
                    "concentration": 0.006836622845644
                },
                "F5": {
                    "barcode": [
                        "TGGAACAA"
                    ],
                    "concentration": 0.011172602056014
                },
                "F6": {
                    "barcode": [
                        "TGGCTTCA"
                    ],
                    "concentration": 0.013830091934371
                },
                "F7": {
                    "barcode": [
                        "TGGTGGTA"
                    ],
                    "concentration": 0.005705061314472
                },
                "F8": {
                    "barcode": [
                        "TTCACGCA"
                    ],
                    "concentration": 0.009698299489041
                },
                "F9": {
                    "barcode": [
                        "AACTCACC"
                    ],
                    "concentration": 0.006385729709147
                },
                "G1": {
                    "barcode": [
                        "AATGTTGC"
                    ],
                    "concentration": 0.005652089152442
                },
                "G10": {
                    "barcode": [
                        "ATTGGCTC"
                    ],
                    "concentration": 0.005770730001811
                },
                "G11": {
                    "barcode": [
                        "CAAGGAGC"
                    ],
                    "concentration": 0.005345229915929
                },
                "G12": {
                    "barcode": [
                        "CACCTTAC"
                    ],
                    "concentration": 0.007806300059837
                },
                "G2": {
                    "barcode": [
                        "ACACGACC"
                    ],
                    "concentration": 0.004725365861382
                },
                "G3": {
                    "barcode": [
                        "ACAGATTC"
                    ],
                    "concentration": 0.006747920895176
                },
                "G4": {
                    "barcode": [
                        "AGATGTAC"
                    ],
                    "concentration": 0.004392860222837
                },
                "G5": {
                    "barcode": [
                        "AGCACCTC"
                    ],
                    "concentration": 0.007892707370326
                },
                "G6": {
                    "barcode": [
                        "AGCCATGC"
                    ],
                    "concentration": 0.003451225391222
                },
                "G7": {
                    "barcode": [
                        "AGGCTAAC"
                    ],
                    "concentration": 0.006582923975072
                },
                "G8": {
                    "barcode": [
                        "ATAGCGAC"
                    ],
                    "concentration": 0.008245271202502
                },
                "G9": {
                    "barcode": [
                        "ATCATTCC"
                    ],
                    "concentration": 0.010641563008338
                },
                "H1": {
                    "barcode": [
                        "CCATCCTC"
                    ],
                    "concentration": 0.009553845749566
                },
                "H10": {
                    "barcode": [
                        "GAGTTAGC"
                    ],
                    "concentration": 0.008770403542851
                },
                "H11": {
                    "barcode": [
                        "GATGAATC"
                    ],
                    "concentration": 0.01008408854993
                },
                "H12": {
                    "barcode": [
                        "GCCAAGAC"
                    ],
                    "concentration": 0.006447098661004
                },
                "H2": {
                    "barcode": [
                        "CCGACAAC"
                    ],
                    "concentration": 0.007027982790361
                },
                "H3": {
                    "barcode": [
                        "CCTAATCC"
                    ],
                    "concentration": 0.005905628773552
                },
                "H4": {
                    "barcode": [
                        "CCTCTATC"
                    ],
                    "concentration": 0.008736135954022
                },
                "H5": {
                    "barcode": [
                        "CGACACAC"
                    ],
                    "concentration": 0.009342239407308
                },
                "H6": {
                    "barcode": [
                        "CGGATTGC"
                    ],
                    "concentration": 0.009122590967207
                },
                "H7": {
                    "barcode": [
                        "CTAAGGTC"
                    ],
                    "concentration": 0.009351989817564
                },
                "H8": {
                    "barcode": [
                        "GAACAGGC"
                    ],
                    "concentration": 0.009236200981292
                },
                "H9": {
                    "barcode": [
                        "GACAGTGC"
                    ],
                    "concentration": 0.006560694197865
                }
            },
            "comment": "BC2: Second round cellular barcode",
            "confidence threshold": 0.999,
            "noise": 0.232146882393514,
            "transform": {
                "token": [
                    "1:48:56"
                ]
            }
        },
        {
            "algorithm": "pamld",
            "codec": {
                "A1": {
                    "barcode": [
                        "AACGTGAT"
                    ],
                    "concentration": 0.007850809653741
                },
                "A10": {
                    "barcode": [
                        "ACAAGCTA"
                    ],
                    "concentration": 0.008798675951794
                },
                "A11": {
                    "barcode": [
                        "CTGTAGCC"
                    ],
                    "concentration": 0.006416195265888
                },
                "A12": {
                    "barcode": [
                        "AGTACAAG"
                    ],
                    "concentration": 0.010798571127858
                },
                "A2": {
                    "barcode": [
                        "AAACATCG"
                    ],
                    "concentration": 0.003077984468429
                },
                "A3": {
                    "barcode": [
                        "ATGCCTAA"
                    ],
                    "concentration": 0.012437969762957
                },
                "A4": {
                    "barcode": [
                        "AGTGGTCA"
                    ],
                    "concentration": 0.007793531217743
                },
                "A5": {
                    "barcode": [
                        "ACCACTGT"
                    ],
                    "concentration": 0.01199538203814
                },
                "A6": {
                    "barcode": [
                        "ACATTGGC"
                    ],
                    "concentration": 0.009853375890481
                },
                "A7": {
                    "barcode": [
                        "CAGATCTG"
                    ],
                    "concentration": 0.005579186772251
                },
                "A8": {
                    "barcode": [
                        "CATCAAGT"
                    ],
                    "concentration": 0.009333494347368
                },
                "A9": {
                    "barcode": [
                        "CGCTGATC"
                    ],
                    "concentration": 0.008964475014116
                },
                "B1": {
                    "barcode": [
                        "AACAACCA"
                    ],
                    "concentration": 0.018147722198489
                },
                "B10": {
                    "barcode": [
                        "ACGTATCA"
                    ],
                    "concentration": 0.010262628075157
                },
                "B11": {
                    "barcode": [
                        "ACTATGCA"
                    ],
                    "concentration": 0.007704569081759
                },
                "B12": {
                    "barcode": [
                        "AGAGTCAA"
                    ],
                    "concentration": 0.004222331881036
                },
                "B2": {
                    "barcode": [
                        "AACCGAGA"
                    ],
                    "concentration": 0.008976969251881
                },
                "B3": {
                    "barcode": [
                        "AACGCTTA"
                    ],
                    "concentration": 0.008534399099831
                },
                "B4": {
                    "barcode": [
                        "AAGACGGA"
                    ],
                    "concentration": 0.009306212625666
                },
                "B5": {
                    "barcode": [
                        "AAGGTACA"
                    ],
                    "concentration": 0.008058080447603
                },
                "B6": {
                    "barcode": [
                        "ACACAGAA"
                    ],
                    "concentration": 0.013049150620145
                },
                "B7": {
                    "barcode": [
                        "ACAGCAGA"
                    ],
                    "concentration": 0.012021995994673
                },
                "B8": {
                    "barcode": [
                        "ACCTCCAA"
                    ],
                    "concentration": 0.009885340754748
                },
                "B9": {
                    "barcode": [
                        "ACGCTCGA"
                    ],
                    "concentration": 0.012528320147581
                },
                "C1": {
                    "barcode": [
                        "AGATCGCA"
                    ],
                    "concentration": 0.00846157755089
                },
                "C10": {
                    "barcode": [
                        "CAGCGTTA"
                    ],
                    "concentration": 0.008262390230124
                },
                "C11": {
                    "barcode": [
                        "CATACCAA"
                    ],
                    "concentration": 0.010879871537167
                },
                "C12": {
                    "barcode": [
                        "CCAGTTCA"
                    ],
                    "concentration": 0.008510271689914
                },
                "C2": {
                    "barcode": [
                        "AGCAGGAA"
                    ],
                    "concentration": 0.009854491761224
                },
                "C3": {
                    "barcode": [
                        "AGTCACTA"
                    ],
                    "concentration": 0.008785048270518
                },
                "C4": {
                    "barcode": [
                        "ATCCTGTA"
                    ],
                    "concentration": 0.012202775841376
                },
                "C5": {
                    "barcode": [
                        "ATTGAGGA"
                    ],
                    "concentration": 0.005926538883051
                },
                "C6": {
                    "barcode": [
                        "CAACCACA"
                    ],
                    "concentration": 0.010885538754719
                },
                "C7": {
                    "barcode": [
                        "GACTAGTA"
                    ],
                    "concentration": 0.009486641017017
                },
                "C8": {
                    "barcode": [
                        "CAATGGAA"
                    ],
                    "concentration": 0.008725828043701
                },
                "C9": {
                    "barcode": [
                        "CACTTCGA"
                    ],
                    "concentration": 0.012506960448561
                },
                "D1": {
                    "barcode": [
                        "CCGAAGTA"
                    ],
                    "concentration": 0.005927338443976
                },
                "D10": {
                    "barcode": [
                        "GAATCTGA"
                    ],
                    "concentration": 0.00941510228011
                },
                "D11": {
                    "barcode": [
                        "CAAGACTA"
                    ],
                    "concentration": 0.00903082978458
                },
                "D12": {
                    "barcode": [
                        "GAGCTGAA"
                    ],
                    "concentration": 0.007508544859162
                },
                "D2": {
                    "barcode": [
                        "CCGTGAGA"
                    ],
                    "concentration": 0.006908909310289
                },
                "D3": {
                    "barcode": [
                        "CCTCCTGA"
                    ],
                    "concentration": 0.008634695670918
                },
                "D4": {
                    "barcode": [
                        "CGAACTTA"
                    ],
                    "concentration": 0.013395351714666
                },
                "D5": {
                    "barcode": [
                        "CGACTGGA"
                    ],
                    "concentration": 0.007020030706219
                },
                "D6": {
                    "barcode": [
                        "CGCATACA"
                    ],
                    "concentration": 0.01187133587164
                },
                "D7": {
                    "barcode": [
                        "CTCAATGA"
                    ],
                    "concentration": 0.014949671795421
                },
                "D8": {
                    "barcode": [
                        "CTGAGCCA"
                    ],
                    "concentration": 0.013528562079471
                },
                "D9": {
                    "barcode": [
                        "CTGGCATA"
                    ],
                    "concentration": 0.008317384206334
                },
                "E1": {
                    "barcode": [
                        "GATAGACA"
                    ],
                    "concentration": 0.014011804402134
                },
                "E10": {
                    "barcode": [
                        "GTCTGTCA"
                    ],
                    "concentration": 0.007479558579003
                },
                "E11": {
                    "barcode": [
                        "GTGTTCTA"
                    ],
                    "concentration": 0.010664069164634
                },
                "E12": {
                    "barcode": [
                        "TAGGATGA"
                    ],
                    "concentration": 0.01180586852594
                },
                "E2": {
                    "barcode": [
                        "GCCACATA"
                    ],
                    "concentration": 0.006378053573809
                },
                "E3": {
                    "barcode": [
                        "GCGAGTAA"
                    ],
                    "concentration": 0.010547043318791
                },
                "E4": {
                    "barcode": [
                        "GCTAACGA"
                    ],
                    "concentration": 0.012556058761241
                },
                "E5": {
                    "barcode": [
                        "GCTCGGTA"
                    ],
                    "concentration": 0.011410832710253
                },
                "E6": {
                    "barcode": [
                        "GGAGAACA"
                    ],
                    "concentration": 0.01212261766196
                },
                "E7": {
                    "barcode": [
                        "GGTGCGAA"
                    ],
                    "concentration": 0.007056872013496
                },
                "E8": {
                    "barcode": [
                        "GTACGCAA"
                    ],
                    "concentration": 0.007160586487881
                },
                "E9": {
                    "barcode": [
                        "GTCGTAGA"
                    ],
                    "concentration": 0.010129769165704
                },
                "F1": {
                    "barcode": [
                        "TATCAGCA"
                    ],
                    "concentration": 0.009685424164127
                },
                "F10": {
                    "barcode": [
                        "AAGAGATC"
                    ],
                    "concentration": 0.006320327032237
                },
                "F11": {
                    "barcode": [
                        "AAGGACAC"
                    ],
                    "concentration": 0.006490325986016
                },
                "F12": {
                    "barcode": [
                        "AATCCGTC"
                    ],
                    "concentration": 0.008355754344392
                },
                "F2": {
                    "barcode": [
                        "TCCGTCTA"
                    ],
                    "concentration": 0.00717290499797
                },
                "F3": {
                    "barcode": [
                        "TCTTCACA"
                    ],
                    "concentration": 0.008471049272627
                },
                "F4": {
                    "barcode": [
                        "TGAAGAGA"
                    ],
                    "concentration": 0.007493599220317
                },
                "F5": {
                    "barcode": [
                        "TGGAACAA"
                    ],
                    "concentration": 0.008339701621188
                },
                "F6": {
                    "barcode": [
                        "TGGCTTCA"
                    ],
                    "concentration": 0.008380444082873
                },
                "F7": {
                    "barcode": [
                        "TGGTGGTA"
                    ],
                    "concentration": 0.005869225301518
                },
                "F8": {
                    "barcode": [
                        "TTCACGCA"
                    ],
                    "concentration": 0.010438417255861
                },
                "F9": {
                    "barcode": [
                        "AACTCACC"
                    ],
                    "concentration": 0.008102311103657
                },
                "G1": {
                    "barcode": [
                        "AATGTTGC"
                    ],
                    "concentration": 0.008122018962522
                },
                "G10": {
                    "barcode": [
                        "ATTGGCTC"
                    ],
                    "concentration": 0.014458495368186
                },
                "G11": {
                    "barcode": [
                        "CAAGGAGC"
                    ],
                    "concentration": 0.008766271768336
                },
                "G12": {
                    "barcode": [
                        "CACCTTAC"
                    ],
                    "concentration": 0.007940676787256
                },
                "G2": {
                    "barcode": [
                        "ACACGACC"
                    ],
                    "concentration": 0.011075623381867
                },
                "G3": {
                    "barcode": [
                        "ACAGATTC"
                    ],
                    "concentration": 0.011230755774254
                },
                "G4": {
                    "barcode": [
                        "AGATGTAC"
                    ],
                    "concentration": 0.008325986076075
                },
                "G5": {
                    "barcode": [
                        "AGCACCTC"
                    ],
                    "concentration": 0.010062526970476
                },
                "G6": {
                    "barcode": [
                        "AGCCATGC"
                    ],
                    "concentration": 0.012825985257987
                },
                "G7": {
                    "barcode": [
                        "AGGCTAAC"
                    ],
                    "concentration": 0.011448078191185
                },
                "G8": {
                    "barcode": [
                        "ATAGCGAC"
                    ],
                    "concentration": 0.008037581814196
                },
                "G9": {
                    "barcode": [
                        "ATCATTCC"
                    ],
                    "concentration": 0.009210186237107
                },
                "H1": {
                    "barcode": [
                        "CCATCCTC"
                    ],
                    "concentration": 0.009138717791271
                },
                "H10": {
                    "barcode": [
                        "GAGTTAGC"
                    ],
                    "concentration": 0.008179719144942
                },
                "H11": {
                    "barcode": [
                        "GATGAATC"
                    ],
                    "concentration": 0.010229942727418
                },
                "H12": {
                    "barcode": [
                        "GCCAAGAC"
                    ],
                    "concentration": 0.008168850388181
                },
                "H2": {
                    "barcode": [
                        "CCGACAAC"
                    ],
                    "concentration": 0.007692241785287
                },
                "H3": {
                    "barcode": [
                        "CCTAATCC"
                    ],
                    "concentration": 0.007523806807824
                },
                "H4": {
                    "barcode": [
                        "CCTCTATC"
                    ],
                    "concentration": 0.009425276912552
                },
                "H5": {
                    "barcode": [
                        "CGACACAC"
                    ],
                    "concentration": 0.005120300305484
                },
                "H6": {
                    "barcode": [
                        "CGGATTGC"
                    ],
                    "concentration": 0.006572979498431
                },
                "H7": {
                    "barcode": [
                        "CTAAGGTC"
                    ],
                    "concentration": 0.006880160262493
                },
                "H8": {
                    "barcode": [
                        "GAACAGGC"
                    ],
                    "concentration": 0.007910627354657
                },
                "H9": {
                    "barcode": [
                        "GACAGTGC"
                    ],
                    "concentration": 0.006038380762452
                }
            },
            "comment": "BC3: Third round cellular barcode",
            "confidence threshold": 0.999,
            "noise": 0.1125791284815,
            "transform": {
                "token": [
                    "1:10:18"
                ]
            }
        }
    ],
    "filter outgoing qc fail": true,
    "input": [
        "SRR6750050.cram?format=cram",
        "SRR6750050.cram?format=cram"
    ],
    "output": [
        "/dev/null"
    ],
    "prior adjusted job url": "SRR6750050_first_adjusted.json?format=json",
    "report url": "SRR6750050_first_report.json?format=json",
    "template": {
        "transform": {
            "token": [
                "0::66"
            ]
        }
    }
}